{
  "a_comp_cor_00": {
    "CumulativeVarianceExplained": 0.0954592502,
    "Mask": "combined",
    "Method": "aCompCor",
    "Retained": true,
    "SingularValue": 103.4298619266,
    "VarianceExplained": 0.0954592502
  },
  "a_comp_cor_01": {
    "CumulativeVarianceExplained": 0.1782796175,
    "Mask": "combined",
    "Method": "aCompCor",
    "Retained": true,
    "SingularValue": 96.3397491811,
    "VarianceExplained": 0.0828203672
  },
  "a_comp_cor_02": {
    "CumulativeVarianceExplained": 0.2453294483,
    "Mask": "combined",
    "Method": "aCompCor",
    "Retained": true,
    "SingularValue": 86.68336832,
    "VarianceExplained": 0.0670498308
  },
  "a_comp_cor_03": {
    "CumulativeVarianceExplained": 0.2733696158,
    "Mask": "combined",
    "Method": "aCompCor",
    "Retained": true,
    "SingularValue": 56.0566625479,
    "VarianceExplained": 0.0280401675
  },
  "a_comp_cor_04": {
    "CumulativeVarianceExplained": 0.2994132348,
    "Mask": "combined",
    "Method": "aCompCor",
    "Retained": true,
    "SingularValue": 54.024107604,
    "VarianceExplained": 0.026043619
  },
  "a_comp_cor_05": {
    "CumulativeVarianceExplained": 0.3214170197,
    "Mask": "combined",
    "Method": "aCompCor",
    "Retained": true,
    "SingularValue": 49.6575890934,
    "VarianceExplained": 0.0220037849
  },
  "a_comp_cor_06": {
    "CumulativeVarianceExplained": 0.3420355769,
    "Mask": "combined",
    "Method": "aCompCor",
    "Retained": true,
    "SingularValue": 48.069108959,
    "VarianceExplained": 0.0206185572
  },
  "a_comp_cor_07": {
    "CumulativeVarianceExplained": 0.3618829411,
    "Mask": "combined",
    "Method": "aCompCor",
    "Retained": true,
    "SingularValue": 47.1615808609,
    "VarianceExplained": 0.0198473641
  },
  "a_comp_cor_08": {
    "CumulativeVarianceExplained": 0.3780511038,
    "Mask": "combined",
    "Method": "aCompCor",
    "Retained": true,
    "SingularValue": 42.5664342058,
    "VarianceExplained": 0.0161681627
  },
  "a_comp_cor_09": {
    "CumulativeVarianceExplained": 0.3932705348,
    "Mask": "combined",
    "Method": "aCompCor",
    "Retained": true,
    "SingularValue": 41.2986773929,
    "VarianceExplained": 0.015219431
  },
  "a_comp_cor_10": {
    "CumulativeVarianceExplained": 0.4081512401,
    "Mask": "combined",
    "Method": "aCompCor",
    "Retained": true,
    "SingularValue": 40.8365170463,
    "VarianceExplained": 0.0148807053
  },
  "a_comp_cor_11": {
    "CumulativeVarianceExplained": 0.4220339333,
    "Mask": "combined",
    "Method": "aCompCor",
    "Retained": true,
    "SingularValue": 39.4433505118,
    "VarianceExplained": 0.0138826932
  },
  "a_comp_cor_12": {
    "CumulativeVarianceExplained": 0.4350566045,
    "Mask": "combined",
    "Method": "aCompCor",
    "Retained": true,
    "SingularValue": 38.2020768051,
    "VarianceExplained": 0.0130226712
  },
  "a_comp_cor_13": {
    "CumulativeVarianceExplained": 0.4469277045,
    "Mask": "combined",
    "Method": "aCompCor",
    "Retained": true,
    "SingularValue": 36.4739179708,
    "VarianceExplained": 0.0118711
  },
  "a_comp_cor_14": {
    "CumulativeVarianceExplained": 0.4583083652,
    "Mask": "combined",
    "Method": "aCompCor",
    "Retained": true,
    "SingularValue": 35.7125344693,
    "VarianceExplained": 0.0113806607
  },
  "a_comp_cor_15": {
    "CumulativeVarianceExplained": 0.4693624898,
    "Mask": "combined",
    "Method": "aCompCor",
    "Retained": true,
    "SingularValue": 35.1964703691,
    "VarianceExplained": 0.0110541246
  },
  "a_comp_cor_16": {
    "CumulativeVarianceExplained": 0.4801685154,
    "Mask": "combined",
    "Method": "aCompCor",
    "Retained": true,
    "SingularValue": 34.7992538246,
    "VarianceExplained": 0.0108060256
  },
  "a_comp_cor_17": {
    "CumulativeVarianceExplained": 0.4906654334,
    "Mask": "combined",
    "Method": "aCompCor",
    "Retained": true,
    "SingularValue": 34.2979243828,
    "VarianceExplained": 0.010496918
  },
  "a_comp_cor_18": {
    "CumulativeVarianceExplained": 0.5004833275,
    "Mask": "combined",
    "Method": "aCompCor",
    "Retained": true,
    "SingularValue": 33.1700483829,
    "VarianceExplained": 0.009817894
  },
  "aroma_motion_1": {
    "CSFFraction": 0.02,
    "EdgeFraction": 0.58,
    "HighFrequencyContent": 0.07,
    "MaximumRpCorrelation": 0.9,
    "Method": {
      "Name": "ICA-AROMA",
      "Version": "0.4.5"
    },
    "ModelVarianceExplained": 0.0382895674,
    "MotionNoise": true,
    "TotalVarianceExplained": 0.0330682486
  },
  "aroma_motion_10": {
    "CSFFraction": 0.26,
    "EdgeFraction": 0.63,
    "HighFrequencyContent": 0.63,
    "MaximumRpCorrelation": 0.28,
    "Method": {
      "Name": "ICA-AROMA",
      "Version": "0.4.5"
    },
    "ModelVarianceExplained": 0.0249878236,
    "MotionNoise": true,
    "TotalVarianceExplained": 0.0215803839
  },
  "aroma_motion_11": {
    "CSFFraction": 0.13,
    "EdgeFraction": 0.56,
    "HighFrequencyContent": 0.57,
    "MaximumRpCorrelation": 0.63,
    "Method": {
      "Name": "ICA-AROMA",
      "Version": "0.4.5"
    },
    "ModelVarianceExplained": 0.0244689098,
    "MotionNoise": true,
    "TotalVarianceExplained": 0.0211322312
  },
  "aroma_motion_12": {
    "CSFFraction": 0.07,
    "EdgeFraction": 0.58,
    "HighFrequencyContent": 0.63,
    "MaximumRpCorrelation": 0.29,
    "Method": {
      "Name": "ICA-AROMA",
      "Version": "0.4.5"
    },
    "ModelVarianceExplained": 0.0233156235,
    "MotionNoise": true,
    "TotalVarianceExplained": 0.0201362117
  },
  "aroma_motion_13": {
    "CSFFraction": 0.11,
    "EdgeFraction": 0.49,
    "HighFrequencyContent": 0.6,
    "MaximumRpCorrelation": 0.42,
    "Method": {
      "Name": "ICA-AROMA",
      "Version": "0.4.5"
    },
    "ModelVarianceExplained": 0.0228150496,
    "MotionNoise": true,
    "TotalVarianceExplained": 0.0197038981
  },
  "aroma_motion_14": {
    "CSFFraction": 0.06,
    "EdgeFraction": 0.58,
    "HighFrequencyContent": 0.12,
    "MaximumRpCorrelation": 0.8,
    "Method": {
      "Name": "ICA-AROMA",
      "Version": "0.4.5"
    },
    "ModelVarianceExplained": 0.0224021731,
    "MotionNoise": true,
    "TotalVarianceExplained": 0.019347323
  },
  "aroma_motion_15": {
    "CSFFraction": 0.02,
    "EdgeFraction": 0.76,
    "HighFrequencyContent": 0.3,
    "MaximumRpCorrelation": 0.85,
    "Method": {
      "Name": "ICA-AROMA",
      "Version": "0.4.5"
    },
    "ModelVarianceExplained": 0.0220799421,
    "MotionNoise": true,
    "TotalVarianceExplained": 0.0190690328
  },
  "aroma_motion_16": {
    "CSFFraction": 0.14,
    "EdgeFraction": 0.7,
    "HighFrequencyContent": 0.56,
    "MaximumRpCorrelation": 0.7,
    "Method": {
      "Name": "ICA-AROMA",
      "Version": "0.4.5"
    },
    "ModelVarianceExplained": 0.0215703771,
    "MotionNoise": true,
    "TotalVarianceExplained": 0.018628954
  },
  "aroma_motion_17": {
    "CSFFraction": 0.02,
    "EdgeFraction": 0.46,
    "HighFrequencyContent": 0.12,
    "MaximumRpCorrelation": 0.47,
    "Method": {
      "Name": "ICA-AROMA",
      "Version": "0.4.5"
    },
    "ModelVarianceExplained": 0.0210699091,
    "MotionNoise": false,
    "TotalVarianceExplained": 0.0181967319
  },
  "aroma_motion_18": {
    "CSFFraction": 0.03,
    "EdgeFraction": 0.87,
    "HighFrequencyContent": 0.45,
    "MaximumRpCorrelation": 0.85,
    "Method": {
      "Name": "ICA-AROMA",
      "Version": "0.4.5"
    },
    "ModelVarianceExplained": 0.0210344568,
    "MotionNoise": true,
    "TotalVarianceExplained": 0.0181661139
  },
  "aroma_motion_19": {
    "CSFFraction": 0.0,
    "EdgeFraction": 0.36,
    "HighFrequencyContent": 0.16,
    "MaximumRpCorrelation": 0.4,
    "Method": {
      "Name": "ICA-AROMA",
      "Version": "0.4.5"
    },
    "ModelVarianceExplained": 0.0208380434,
    "MotionNoise": false,
    "TotalVarianceExplained": 0.0179964843
  },
  "aroma_motion_2": {
    "CSFFraction": 0.01,
    "EdgeFraction": 0.8,
    "HighFrequencyContent": 0.12,
    "MaximumRpCorrelation": 0.71,
    "Method": {
      "Name": "ICA-AROMA",
      "Version": "0.4.5"
    },
    "ModelVarianceExplained": 0.0372828046,
    "MotionNoise": true,
    "TotalVarianceExplained": 0.032198772
  },
  "aroma_motion_20": {
    "CSFFraction": 0.02,
    "EdgeFraction": 0.41,
    "HighFrequencyContent": 0.37,
    "MaximumRpCorrelation": 0.72,
    "Method": {
      "Name": "ICA-AROMA",
      "Version": "0.4.5"
    },
    "ModelVarianceExplained": 0.0207980222,
    "MotionNoise": true,
    "TotalVarianceExplained": 0.0179619206
  },
  "aroma_motion_21": {
    "CSFFraction": 0.06,
    "EdgeFraction": 0.55,
    "HighFrequencyContent": 0.3,
    "MaximumRpCorrelation": 0.67,
    "Method": {
      "Name": "ICA-AROMA",
      "Version": "0.4.5"
    },
    "ModelVarianceExplained": 0.0207508833,
    "MotionNoise": true,
    "TotalVarianceExplained": 0.0179212097
  },
  "aroma_motion_22": {
    "CSFFraction": 0.16,
    "EdgeFraction": 0.59,
    "HighFrequencyContent": 0.6,
    "MaximumRpCorrelation": 0.51,
    "Method": {
      "Name": "ICA-AROMA",
      "Version": "0.4.5"
    },
    "ModelVarianceExplained": 0.0201166797,
    "MotionNoise": true,
    "TotalVarianceExplained": 0.0173734887
  },
  "aroma_motion_23": {
    "CSFFraction": 0.02,
    "EdgeFraction": 0.36,
    "HighFrequencyContent": 0.16,
    "MaximumRpCorrelation": 0.28,
    "Method": {
      "Name": "ICA-AROMA",
      "Version": "0.4.5"
    },
    "ModelVarianceExplained": 0.0199164014,
    "MotionNoise": false,
    "TotalVarianceExplained": 0.0172005211
  },
  "aroma_motion_24": {
    "CSFFraction": 0.14,
    "EdgeFraction": 0.65,
    "HighFrequencyContent": 0.42,
    "MaximumRpCorrelation": 0.52,
    "Method": {
      "Name": "ICA-AROMA",
      "Version": "0.4.5"
    },
    "ModelVarianceExplained": 0.0196688979,
    "MotionNoise": true,
    "TotalVarianceExplained": 0.0169867682
  },
  "aroma_motion_25": {
    "CSFFraction": 0.02,
    "EdgeFraction": 0.77,
    "HighFrequencyContent": 0.42,
    "MaximumRpCorrelation": 0.84,
    "Method": {
      "Name": "ICA-AROMA",
      "Version": "0.4.5"
    },
    "ModelVarianceExplained": 0.0193110974,
    "MotionNoise": true,
    "TotalVarianceExplained": 0.0166777588
  },
  "aroma_motion_26": {
    "CSFFraction": 0.3,
    "EdgeFraction": 0.7,
    "HighFrequencyContent": 0.62,
    "MaximumRpCorrelation": 0.31,
    "Method": {
      "Name": "ICA-AROMA",
      "Version": "0.4.5"
    },
    "ModelVarianceExplained": 0.0192681151,
    "MotionNoise": true,
    "TotalVarianceExplained": 0.0166406377
  },
  "aroma_motion_27": {
    "CSFFraction": 0.03,
    "EdgeFraction": 0.41,
    "HighFrequencyContent": 0.34,
    "MaximumRpCorrelation": 0.54,
    "Method": {
      "Name": "ICA-AROMA",
      "Version": "0.4.5"
    },
    "ModelVarianceExplained": 0.0191891866,
    "MotionNoise": false,
    "TotalVarianceExplained": 0.0165724723
  },
  "aroma_motion_28": {
    "CSFFraction": 0.01,
    "EdgeFraction": 0.4,
    "HighFrequencyContent": 0.15,
    "MaximumRpCorrelation": 0.37,
    "Method": {
      "Name": "ICA-AROMA",
      "Version": "0.4.5"
    },
    "ModelVarianceExplained": 0.0191415068,
    "MotionNoise": false,
    "TotalVarianceExplained": 0.0165312942
  },
  "aroma_motion_29": {
    "CSFFraction": 0.02,
    "EdgeFraction": 0.38,
    "HighFrequencyContent": 0.18,
    "MaximumRpCorrelation": 0.64,
    "Method": {
      "Name": "ICA-AROMA",
      "Version": "0.4.5"
    },
    "ModelVarianceExplained": 0.0191307415,
    "MotionNoise": false,
    "TotalVarianceExplained": 0.016521997
  },
  "aroma_motion_3": {
    "CSFFraction": 0.2,
    "EdgeFraction": 0.56,
    "HighFrequencyContent": 0.63,
    "MaximumRpCorrelation": 0.24,
    "Method": {
      "Name": "ICA-AROMA",
      "Version": "0.4.5"
    },
    "ModelVarianceExplained": 0.0325896297,
    "MotionNoise": true,
    "TotalVarianceExplained": 0.0281455772
  },
  "aroma_motion_30": {
    "CSFFraction": 0.0,
    "EdgeFraction": 0.36,
    "HighFrequencyContent": 0.25,
    "MaximumRpCorrelation": 0.27,
    "Method": {
      "Name": "ICA-AROMA",
      "Version": "0.4.5"
    },
    "ModelVarianceExplained": 0.0190553855,
    "MotionNoise": false,
    "TotalVarianceExplained": 0.0164569168
  },
  "aroma_motion_31": {
    "CSFFraction": 0.02,
    "EdgeFraction": 0.52,
    "HighFrequencyContent": 0.24,
    "MaximumRpCorrelation": 0.57,
    "Method": {
      "Name": "ICA-AROMA",
      "Version": "0.4.5"
    },
    "ModelVarianceExplained": 0.0188564829,
    "MotionNoise": false,
    "TotalVarianceExplained": 0.0162851374
  },
  "aroma_motion_32": {
    "CSFFraction": 0.03,
    "EdgeFraction": 0.49,
    "HighFrequencyContent": 0.3,
    "MaximumRpCorrelation": 0.52,
    "Method": {
      "Name": "ICA-AROMA",
      "Version": "0.4.5"
    },
    "ModelVarianceExplained": 0.0188285927,
    "MotionNoise": false,
    "TotalVarianceExplained": 0.0162610504
  },
  "aroma_motion_33": {
    "CSFFraction": 0.01,
    "EdgeFraction": 0.53,
    "HighFrequencyContent": 0.16,
    "MaximumRpCorrelation": 0.49,
    "Method": {
      "Name": "ICA-AROMA",
      "Version": "0.4.5"
    },
    "ModelVarianceExplained": 0.0184689902,
    "MotionNoise": false,
    "TotalVarianceExplained": 0.0159504847
  },
  "aroma_motion_34": {
    "CSFFraction": 0.01,
    "EdgeFraction": 0.51,
    "HighFrequencyContent": 0.25,
    "MaximumRpCorrelation": 0.33,
    "Method": {
      "Name": "ICA-AROMA",
      "Version": "0.4.5"
    },
    "ModelVarianceExplained": 0.0182538261,
    "MotionNoise": false,
    "TotalVarianceExplained": 0.0157646612
  },
  "aroma_motion_35": {
    "CSFFraction": 0.09,
    "EdgeFraction": 0.48,
    "HighFrequencyContent": 0.68,
    "MaximumRpCorrelation": 0.51,
    "Method": {
      "Name": "ICA-AROMA",
      "Version": "0.4.5"
    },
    "ModelVarianceExplained": 0.0176519685,
    "MotionNoise": true,
    "TotalVarianceExplained": 0.0152448753
  },
  "aroma_motion_36": {
    "CSFFraction": 0.04,
    "EdgeFraction": 0.74,
    "HighFrequencyContent": 0.37,
    "MaximumRpCorrelation": 0.8,
    "Method": {
      "Name": "ICA-AROMA",
      "Version": "0.4.5"
    },
    "ModelVarianceExplained": 0.0175470214,
    "MotionNoise": true,
    "TotalVarianceExplained": 0.0151542393
  },
  "aroma_motion_37": {
    "CSFFraction": 0.01,
    "EdgeFraction": 0.77,
    "HighFrequencyContent": 0.27,
    "MaximumRpCorrelation": 0.88,
    "Method": {
      "Name": "ICA-AROMA",
      "Version": "0.4.5"
    },
    "ModelVarianceExplained": 0.0174913212,
    "MotionNoise": true,
    "TotalVarianceExplained": 0.0151061346
  },
  "aroma_motion_38": {
    "CSFFraction": 0.02,
    "EdgeFraction": 0.43,
    "HighFrequencyContent": 0.12,
    "MaximumRpCorrelation": 0.72,
    "Method": {
      "Name": "ICA-AROMA",
      "Version": "0.4.5"
    },
    "ModelVarianceExplained": 0.0174411853,
    "MotionNoise": false,
    "TotalVarianceExplained": 0.0150628354
  },
  "aroma_motion_39": {
    "CSFFraction": 0.03,
    "EdgeFraction": 0.49,
    "HighFrequencyContent": 0.15,
    "MaximumRpCorrelation": 0.86,
    "Method": {
      "Name": "ICA-AROMA",
      "Version": "0.4.5"
    },
    "ModelVarianceExplained": 0.0168840964,
    "MotionNoise": true,
    "TotalVarianceExplained": 0.0145817134
  },
  "aroma_motion_4": {
    "CSFFraction": 0.01,
    "EdgeFraction": 0.5,
    "HighFrequencyContent": 0.1,
    "MaximumRpCorrelation": 0.56,
    "Method": {
      "Name": "ICA-AROMA",
      "Version": "0.4.5"
    },
    "ModelVarianceExplained": 0.0319432471,
    "MotionNoise": false,
    "TotalVarianceExplained": 0.0275873379
  },
  "aroma_motion_40": {
    "CSFFraction": 0.15,
    "EdgeFraction": 0.42,
    "HighFrequencyContent": 0.68,
    "MaximumRpCorrelation": 0.35,
    "Method": {
      "Name": "ICA-AROMA",
      "Version": "0.4.5"
    },
    "ModelVarianceExplained": 0.0167626813,
    "MotionNoise": true,
    "TotalVarianceExplained": 0.0144768549
  },
  "aroma_motion_41": {
    "CSFFraction": 0.0,
    "EdgeFraction": 0.4,
    "HighFrequencyContent": 0.22,
    "MaximumRpCorrelation": 0.51,
    "Method": {
      "Name": "ICA-AROMA",
      "Version": "0.4.5"
    },
    "ModelVarianceExplained": 0.0166206875,
    "MotionNoise": false,
    "TotalVarianceExplained": 0.0143542239
  },
  "aroma_motion_42": {
    "CSFFraction": 0.0,
    "EdgeFraction": 0.32,
    "HighFrequencyContent": 0.16,
    "MaximumRpCorrelation": 0.61,
    "Method": {
      "Name": "ICA-AROMA",
      "Version": "0.4.5"
    },
    "ModelVarianceExplained": 0.0163306611,
    "MotionNoise": false,
    "TotalVarianceExplained": 0.0141037467
  },
  "aroma_motion_43": {
    "CSFFraction": 0.01,
    "EdgeFraction": 0.49,
    "HighFrequencyContent": 0.19,
    "MaximumRpCorrelation": 0.58,
    "Method": {
      "Name": "ICA-AROMA",
      "Version": "0.4.5"
    },
    "ModelVarianceExplained": 0.0161726332,
    "MotionNoise": false,
    "TotalVarianceExplained": 0.0139672681
  },
  "aroma_motion_44": {
    "CSFFraction": 0.01,
    "EdgeFraction": 0.39,
    "HighFrequencyContent": 0.27,
    "MaximumRpCorrelation": 0.54,
    "Method": {
      "Name": "ICA-AROMA",
      "Version": "0.4.5"
    },
    "ModelVarianceExplained": 0.0161275141,
    "MotionNoise": false,
    "TotalVarianceExplained": 0.0139283017
  },
  "aroma_motion_45": {
    "CSFFraction": 0.18,
    "EdgeFraction": 0.65,
    "HighFrequencyContent": 0.33,
    "MaximumRpCorrelation": 0.28,
    "Method": {
      "Name": "ICA-AROMA",
      "Version": "0.4.5"
    },
    "ModelVarianceExplained": 0.0156826797,
    "MotionNoise": true,
    "TotalVarianceExplained": 0.0135441266
  },
  "aroma_motion_46": {
    "CSFFraction": 0.02,
    "EdgeFraction": 0.47,
    "HighFrequencyContent": 0.31,
    "MaximumRpCorrelation": 0.27,
    "Method": {
      "Name": "ICA-AROMA",
      "Version": "0.4.5"
    },
    "ModelVarianceExplained": 0.0149675951,
    "MotionNoise": false,
    "TotalVarianceExplained": 0.0129265538
  },
  "aroma_motion_5": {
    "CSFFraction": 0.05,
    "EdgeFraction": 0.63,
    "HighFrequencyContent": 0.12,
    "MaximumRpCorrelation": 0.79,
    "Method": {
      "Name": "ICA-AROMA",
      "Version": "0.4.5"
    },
    "ModelVarianceExplained": 0.0308513008,
    "MotionNoise": true,
    "TotalVarianceExplained": 0.0266442938
  },
  "aroma_motion_6": {
    "CSFFraction": 0.0,
    "EdgeFraction": 0.51,
    "HighFrequencyContent": 0.12,
    "MaximumRpCorrelation": 0.59,
    "Method": {
      "Name": "ICA-AROMA",
      "Version": "0.4.5"
    },
    "ModelVarianceExplained": 0.0302412689,
    "MotionNoise": false,
    "TotalVarianceExplained": 0.0261174483
  },
  "aroma_motion_7": {
    "CSFFraction": 0.01,
    "EdgeFraction": 0.69,
    "HighFrequencyContent": 0.13,
    "MaximumRpCorrelation": 0.56,
    "Method": {
      "Name": "ICA-AROMA",
      "Version": "0.4.5"
    },
    "ModelVarianceExplained": 0.0290618409,
    "MotionNoise": true,
    "TotalVarianceExplained": 0.0250988518
  },
  "aroma_motion_8": {
    "CSFFraction": 0.0,
    "EdgeFraction": 0.52,
    "HighFrequencyContent": 0.1,
    "MaximumRpCorrelation": 0.33,
    "Method": {
      "Name": "ICA-AROMA",
      "Version": "0.4.5"
    },
    "ModelVarianceExplained": 0.0285765852,
    "MotionNoise": false,
    "TotalVarianceExplained": 0.0246797676
  },
  "aroma_motion_9": {
    "CSFFraction": 0.01,
    "EdgeFraction": 0.29,
    "HighFrequencyContent": 0.16,
    "MaximumRpCorrelation": 0.33,
    "Method": {
      "Name": "ICA-AROMA",
      "Version": "0.4.5"
    },
    "ModelVarianceExplained": 0.026146593,
    "MotionNoise": false,
    "TotalVarianceExplained": 0.0225811388
  },
  "c_comp_cor_00": {
    "CumulativeVarianceExplained": 0.192510775,
    "Mask": "CSF",
    "Method": "aCompCor",
    "Retained": true,
    "SingularValue": 64.3483819501,
    "VarianceExplained": 0.192510775
  },
  "c_comp_cor_01": {
    "CumulativeVarianceExplained": 0.3177696479,
    "Mask": "CSF",
    "Method": "aCompCor",
    "Retained": true,
    "SingularValue": 51.9056171984,
    "VarianceExplained": 0.1252588729
  },
  "c_comp_cor_02": {
    "CumulativeVarianceExplained": 0.4356094634,
    "Mask": "CSF",
    "Method": "aCompCor",
    "Retained": true,
    "SingularValue": 50.3449758361,
    "VarianceExplained": 0.1178398155
  },
  "c_comp_cor_03": {
    "CumulativeVarianceExplained": 0.4865451312,
    "Mask": "CSF",
    "Method": "aCompCor",
    "Retained": true,
    "SingularValue": 33.0994755185,
    "VarianceExplained": 0.0509356678
  },
  "c_comp_cor_04": {
    "CumulativeVarianceExplained": 0.5309442566,
    "Mask": "CSF",
    "Method": "aCompCor",
    "Retained": true,
    "SingularValue": 30.9027634362,
    "VarianceExplained": 0.0443991254
  },
  "csf": {
    "Method": "Mean"
  },
  "csf_wm": {
    "Method": "Mean"
  },
  "global_signal": {
    "Method": "Mean"
  },
  "t_comp_cor_00": {
    "CumulativeVarianceExplained": 0.2025025056,
    "Method": "tCompCor",
    "Retained": true,
    "SingularValue": 109.2218961789,
    "VarianceExplained": 0.2025025056
  },
  "t_comp_cor_01": {
    "CumulativeVarianceExplained": 0.3638810524,
    "Method": "tCompCor",
    "Retained": true,
    "SingularValue": 97.5028727283,
    "VarianceExplained": 0.1613785468
  },
  "t_comp_cor_02": {
    "CumulativeVarianceExplained": 0.5113694976,
    "Method": "tCompCor",
    "Retained": true,
    "SingularValue": 93.2123613389,
    "VarianceExplained": 0.1474884452
  },
  "tcompcor": {
    "Method": "Mean"
  },
  "w_comp_cor_00": {
    "CumulativeVarianceExplained": 0.0604320576,
    "Mask": "WM",
    "Method": "aCompCor",
    "Retained": true,
    "SingularValue": 62.3132489759,
    "VarianceExplained": 0.0604320576
  },
  "w_comp_cor_01": {
    "CumulativeVarianceExplained": 0.1138323394,
    "Mask": "WM",
    "Method": "aCompCor",
    "Retained": true,
    "SingularValue": 58.5758338155,
    "VarianceExplained": 0.0534002818
  },
  "w_comp_cor_02": {
    "CumulativeVarianceExplained": 0.1616185816,
    "Mask": "WM",
    "Method": "aCompCor",
    "Retained": true,
    "SingularValue": 55.4112752121,
    "VarianceExplained": 0.0477862422
  },
  "w_comp_cor_03": {
    "CumulativeVarianceExplained": 0.1918131014,
    "Mask": "WM",
    "Method": "aCompCor",
    "Retained": true,
    "SingularValue": 44.0464355075,
    "VarianceExplained": 0.0301945198
  },
  "w_comp_cor_04": {
    "CumulativeVarianceExplained": 0.2167334589,
    "Mask": "WM",
    "Method": "aCompCor",
    "Retained": true,
    "SingularValue": 40.0150937543,
    "VarianceExplained": 0.0249203575
  },
  "w_comp_cor_05": {
    "CumulativeVarianceExplained": 0.2392685014,
    "Mask": "WM",
    "Method": "aCompCor",
    "Retained": true,
    "SingularValue": 38.0518604533,
    "VarianceExplained": 0.0225350425
  },
  "w_comp_cor_06": {
    "CumulativeVarianceExplained": 0.2596075688,
    "Mask": "WM",
    "Method": "aCompCor",
    "Retained": true,
    "SingularValue": 36.1503264188,
    "VarianceExplained": 0.0203390674
  },
  "w_comp_cor_07": {
    "CumulativeVarianceExplained": 0.2793813973,
    "Mask": "WM",
    "Method": "aCompCor",
    "Retained": true,
    "SingularValue": 35.644463848,
    "VarianceExplained": 0.0197738285
  },
  "w_comp_cor_08": {
    "CumulativeVarianceExplained": 0.2956646116,
    "Mask": "WM",
    "Method": "aCompCor",
    "Retained": true,
    "SingularValue": 32.3457163525,
    "VarianceExplained": 0.0162832143
  },
  "w_comp_cor_09": {
    "CumulativeVarianceExplained": 0.3116786804,
    "Mask": "WM",
    "Method": "aCompCor",
    "Retained": true,
    "SingularValue": 32.0772811513,
    "VarianceExplained": 0.0160140689
  },
  "w_comp_cor_10": {
    "CumulativeVarianceExplained": 0.3263001519,
    "Mask": "WM",
    "Method": "aCompCor",
    "Retained": true,
    "SingularValue": 30.6508304569,
    "VarianceExplained": 0.0146214715
  },
  "w_comp_cor_11": {
    "CumulativeVarianceExplained": 0.3406925925,
    "Mask": "WM",
    "Method": "aCompCor",
    "Retained": true,
    "SingularValue": 30.409825468,
    "VarianceExplained": 0.0143924406
  },
  "w_comp_cor_12": {
    "CumulativeVarianceExplained": 0.3542019069,
    "Mask": "WM",
    "Method": "aCompCor",
    "Retained": true,
    "SingularValue": 29.4620769071,
    "VarianceExplained": 0.0135093144
  },
  "w_comp_cor_13": {
    "CumulativeVarianceExplained": 0.3669926265,
    "Mask": "WM",
    "Method": "aCompCor",
    "Retained": true,
    "SingularValue": 28.6677886435,
    "VarianceExplained": 0.0127907196
  },
  "w_comp_cor_14": {
    "CumulativeVarianceExplained": 0.3796680653,
    "Mask": "WM",
    "Method": "aCompCor",
    "Retained": true,
    "SingularValue": 28.538307108,
    "VarianceExplained": 0.0126754389
  },
  "w_comp_cor_15": {
    "CumulativeVarianceExplained": 0.3920738737,
    "Mask": "WM",
    "Method": "aCompCor",
    "Retained": true,
    "SingularValue": 28.2331437205,
    "VarianceExplained": 0.0124058084
  },
  "w_comp_cor_16": {
    "CumulativeVarianceExplained": 0.4038072799,
    "Mask": "WM",
    "Method": "aCompCor",
    "Retained": true,
    "SingularValue": 27.4573587505,
    "VarianceExplained": 0.0117334062
  },
  "w_comp_cor_17": {
    "CumulativeVarianceExplained": 0.415278812,
    "Mask": "WM",
    "Method": "aCompCor",
    "Retained": true,
    "SingularValue": 27.149223825,
    "VarianceExplained": 0.0114715321
  },
  "w_comp_cor_18": {
    "CumulativeVarianceExplained": 0.4265450617,
    "Mask": "WM",
    "Method": "aCompCor",
    "Retained": true,
    "SingularValue": 26.9052103159,
    "VarianceExplained": 0.0112662497
  },
  "w_comp_cor_19": {
    "CumulativeVarianceExplained": 0.4373947169,
    "Mask": "WM",
    "Method": "aCompCor",
    "Retained": true,
    "SingularValue": 26.403084928,
    "VarianceExplained": 0.0108496552
  },
  "w_comp_cor_20": {
    "CumulativeVarianceExplained": 0.4481471512,
    "Mask": "WM",
    "Method": "aCompCor",
    "Retained": true,
    "SingularValue": 26.2845231792,
    "VarianceExplained": 0.0107524343
  },
  "w_comp_cor_21": {
    "CumulativeVarianceExplained": 0.4587780064,
    "Mask": "WM",
    "Method": "aCompCor",
    "Retained": true,
    "SingularValue": 26.1354996685,
    "VarianceExplained": 0.0106308553
  },
  "w_comp_cor_22": {
    "CumulativeVarianceExplained": 0.46932885,
    "Mask": "WM",
    "Method": "aCompCor",
    "Retained": true,
    "SingularValue": 26.0369612157,
    "VarianceExplained": 0.0105508435
  },
  "w_comp_cor_23": {
    "CumulativeVarianceExplained": 0.4796553555,
    "Mask": "WM",
    "Method": "aCompCor",
    "Retained": true,
    "SingularValue": 25.7586676862,
    "VarianceExplained": 0.0103265055
  },
  "w_comp_cor_24": {
    "CumulativeVarianceExplained": 0.4897560255,
    "Mask": "WM",
    "Method": "aCompCor",
    "Retained": true,
    "SingularValue": 25.4754459478,
    "VarianceExplained": 0.0101006699
  },
  "w_comp_cor_25": {
    "CumulativeVarianceExplained": 0.499565336,
    "Mask": "WM",
    "Method": "aCompCor",
    "Retained": true,
    "SingularValue": 25.1053307419,
    "VarianceExplained": 0.0098093106
  },
  "w_comp_cor_26": {
    "CumulativeVarianceExplained": 0.5092298356,
    "Mask": "WM",
    "Method": "aCompCor",
    "Retained": true,
    "SingularValue": 24.9193317282,
    "VarianceExplained": 0.0096644996
  },
  "white_matter": {
    "Method": "Mean"
  }
}